{
  "version": "7",
  "dialect": "postgresql",
  "entries": [
    {
      "idx": 0,
      "version": "7",
      "when": 1780659815954,
      "tag": "0000_freezing_kronos",
      "breakpoints": true
    },
    {
      "idx": 1,
      "version": "7",
      "when": 1780739327539,
      "tag": "0001_magenta_tusk",
      "breakpoints": true
    },
    {
      "idx": 2,
      "version": "7",
      "when": 1780768286297,
      "tag": "0002_slow_midnight",
      "breakpoints": true
    },
    {
      "idx": 3,
      "version": "7",
      "when": 1780770000000,
      "tag": "0003_walrus_context",
      "breakpoints": true
    },
    {
      "idx": 4,
      "version": "7",
      "when": 1781200000000,
      "tag": "0004_market",
      "breakpoints": true
    },
    {
      "idx": 5,
      "version": "7",
      "when": 1781700000000,
      "tag": "0005_hardening",
      "breakpoints": true
    },
    {
      "idx": 6,
      "version": "7",
      "when": 1781800000000,
      "tag": "0006_fold_github_into_social",
      "breakpoints": true
    },
    {
      "idx": 7,
      "version": "7",
      "when": 1781820000000,
      "tag": "0007_vault",
      "breakpoints": true
    }
  ]
}